README.md
setup.py
gff2json/__init__.py
gff2json/gff2json.py
gff2json.egg-info/PKG-INFO
gff2json.egg-info/SOURCES.txt
gff2json.egg-info/dependency_links.txt
gff2json.egg-info/entry_points.txt
gff2json.egg-info/top_level.txt